machinestate.py
MachineState-0.5.1.dist-info/LICENSE
MachineState-0.5.1.dist-info/METADATA
MachineState-0.5.1.dist-info/WHEEL
MachineState-0.5.1.dist-info/top_level.txt
MachineState-0.5.1.dist-info/RECORD
